json2cmake/__init__.py
json2cmake-0.6.3.dist-info/METADATA
json2cmake-0.6.3.dist-info/RECORD
json2cmake-0.6.3.dist-info/WHEEL
json2cmake-0.6.3.dist-info/entry_points.txt
json2cmake-0.6.3.dist-info/top_level.txt
