Metadata-Version: 2.1
Name: json2cmake
Version: 0.6.3
Summary: Generate CMakeLists.txt from a compile_commands.json
Home-page: https://github.com/AbigailBuccaneer/json2cmake
Author: AbigailBuccaneer
Author-email: UNKNOWN
License: MIT
Keywords: c c++ cmake development
Platform: UNKNOWN
Classifier: Development Status :: 4 - Beta
Classifier: Intended Audience :: Developers
Classifier: Topic :: Software Development :: Build Tools
Classifier: License :: OSI Approved :: MIT License
Classifier: Programming Language :: Python :: 2
Classifier: Programming Language :: Python :: 2.7
Classifier: Programming Language :: Python :: 3
Classifier: Programming Language :: Python :: 3.4
Classifier: Programming Language :: Python :: 3.5
Classifier: Programming Language :: Python :: 3.6
